{
  "sessions": [
    {
      "sessionId": "VINSMOKE@289aa924-526b-47a5-9932-c344ef134c1e",
      "createdAt": "2025-11-02T06:40:22.078Z",
      "expiresAt": "2025-11-03T06:40:22.078Z"
    },
    {
      "sessionId": "VINSMOKE@75d9cd4c-6f09-4526-beee-14d04ff4a555",
      "createdAt": "2025-11-02T06:49:16.278Z",
      "expiresAt": "2025-11-03T06:49:16.278Z"
    },
    {
      "sessionId": "VINSMOKE@6fa2f18d-5f75-4147-a6fe-ccfba557f936",
      "createdAt": "2025-11-02T06:51:06.510Z",
      "expiresAt": "2025-11-03T06:51:06.511Z"
    },
    {
      "sessionId": "VINSMOKE@de052076-34ba-4929-bfd9-cd9b58806b48",
      "createdAt": "2025-11-02T06:53:39.756Z",
      "expiresAt": "2025-11-03T06:53:39.756Z"
    },
    {
      "sessionId": "VINSMOKE@c19dbd80-9fe9-4551-a6d3-6272e2d671a1",
      "createdAt": "2025-12-28T06:31:33.314Z",
      "expiresAt": "2026-12-28T06:31:33.314Z",
      "isPermanent": true
    },
    {
      "sessionId": "VINSMOKE@264219d2-34ad-41ef-834d-ad2fca4cb17d",
      "createdAt": "2025-12-28T07:30:10.753Z",
      "expiresAt": "2026-12-28T07:30:10.753Z",
      "isPermanent": true
    },
    {
      "sessionId": "VINSMOKE@9fc3dfdc-ccea-4b5a-bcb3-cf31b21e0cad",
      "userPhoneNumber": "994403163701",
      "createdAt": "2025-01-08T13:01:54.048Z",
      "connectedAt": "2025-01-08T13:01:54.048Z",
      "expiresAt": "2026-02-07T13:01:54.048Z",
      "isPermanent": true,
      "isGood": true,
      "status": "active"
    }
  ]
}
